WebDeploy/__init__.py
WebDeploy/scripts/__init__.py
WebDeploy/scripts/config.py
WebDeploy/scripts/config_db.py
WebDeploy/scripts/deploy_django.py
WebDeploy/scripts/deploy_flask.py
WebDeploy/scripts/runner.py
WebDeploy-1.1.0.dist-info/LICENSE
WebDeploy-1.1.0.dist-info/METADATA
WebDeploy-1.1.0.dist-info/WHEEL
WebDeploy-1.1.0.dist-info/entry_points.txt
WebDeploy-1.1.0.dist-info/top_level.txt
WebDeploy-1.1.0.dist-info/RECORD
