Metadata-Version: 2.1
Name: WebDeploy
Version: 1.1.0
Summary: WebDeploy is a python package for deploying Flask/Django applications at ease.
Home-page: https://github.com/idaljeetsingh/WebDeploy
Author: Daljeet Singh Chhabra
Author-email: idaljeetsingh@outlook.com
License: MIT
Platform: UNKNOWN
Classifier: Intended Audience :: Developers
Classifier: License :: OSI Approved :: MIT License
Classifier: Programming Language :: Python
Classifier: Programming Language :: Python :: 3.5
Classifier: Programming Language :: Python :: 3.6
Classifier: Programming Language :: Python :: 3.7
Classifier: Programming Language :: Python :: 3.8
Classifier: Programming Language :: Python :: 3.9
Classifier: Topic :: Software Development :: Libraries
Classifier: Topic :: Software Development :: Libraries :: Python Modules
Classifier: Topic :: Internet :: WWW/HTTP :: HTTP Servers
Requires-Python: >=3.5
